echochamber/__init__.py
echochamber/crawler.py
echochamber/esn.py
echochamber/minimalist_crawler.py
echochamber/train.py
echochamber-0.0.6.dist-info/METADATA
echochamber-0.0.6.dist-info/WHEEL
echochamber-0.0.6.dist-info/entry_points.txt
echochamber-0.0.6.dist-info/top_level.txt
echochamber-0.0.6.dist-info/RECORD
