Metadata-Version: 2.1
Name: echochamber
Version: 0.0.6
Summary: Using an Echo State Network to crawl Microprediction.Org
Home-page: https://github.com/microprediction/echochamber
Author: microprediction
Author-email: info@microprediction.com
License: MIT
Platform: UNKNOWN
Classifier: License :: OSI Approved :: MIT License
Classifier: Programming Language :: Python :: 3
Classifier: Programming Language :: Python :: 3.7
Requires-Dist: pathlib
Requires-Dist: microprediction
Requires-Dist: numpy
